{
  "info": {
    "description": "data",
    "version": "1.0",
    "year": 2025,
    "contributor": "search engine",
    "source": "no_augmentation",
    "license": {
      "name": "Creative Commons Attribution 4.0 International",
      "url": "https://creativecommons.org/licenses/by/4.0/"
    },
    "leaf_info": {
      "leaf_number": 136.0,
      "source": "plant_village_classification",
      "original_filename": "RS_HL 5143.JPG"
    }
  },
  "images": [
    {
      "id": 6547060757,
      "width": 256,
      "height": 256,
      "file_name": "image (1475).JPG",
      "size": 20108,
      "format": "JPG",
      "url": "",
      "hash": "",
      "status": "success",
      "original_filename": "RS_HL 5143.JPG",
      "pvc_filename": "fbc8e5c2-1bbb-4e1b-a836-69f71f911f3c___RS_HL 5143.JPG"
    }
  ],
  "annotations": [
    {
      "id": 6985975767,
      "image_id": 6547060757,
      "category_id": 2000000004,
      "segmentation": [],
      "area": 2025,
      "bbox": [
        41,
        126,
        139,
        115
      ]
    }
  ],
  "categories": [
    {
      "id": 2000000004,
      "name": "healthy",
      "supercategory": "Blueberry"
    }
  ]
}