{
  "info": {
    "description": "data",
    "version": "1.0",
    "year": 2025,
    "contributor": "search engine",
    "source": "no_augmentation",
    "license": {
      "name": "Creative Commons Attribution 4.0 International",
      "url": "https://creativecommons.org/licenses/by/4.0/"
    },
    "leaf_info": {
      "leaf_number": 108.0,
      "source": "plant_village_classification",
      "original_filename": "RS_HL 2652.JPG"
    }
  },
  "images": [
    {
      "id": 9967736525,
      "width": 256,
      "height": 256,
      "file_name": "image (625).JPG",
      "size": 16158,
      "format": "JPG",
      "url": "",
      "hash": "",
      "status": "success",
      "original_filename": "RS_HL 2652.JPG",
      "pvc_filename": "608e5585-86a8-4d25-91a7-e841f3ea4d60___RS_HL 2652.JPG"
    }
  ],
  "annotations": [
    {
      "id": 2095993535,
      "image_id": 9967736525,
      "category_id": 2000000004,
      "segmentation": [],
      "area": 9720,
      "bbox": [
        6,
        17,
        124,
        214
      ]
    }
  ],
  "categories": [
    {
      "id": 2000000004,
      "name": "healthy",
      "supercategory": "Blueberry"
    }
  ]
}