{
  "info": {
    "description": "data",
    "version": "1.0",
    "year": 2025,
    "contributor": "search engine",
    "source": "augmented",
    "license": {
      "name": "Creative Commons Attribution 4.0 International",
      "url": "https://creativecommons.org/licenses/by/4.0/"
    }
  },
  "images": [
    {
      "id": 8341667948,
      "width": 256,
      "height": 256,
      "file_name": "image (762).JPG",
      "size": 17400,
      "format": "JPG",
      "url": "",
      "hash": "",
      "status": "success"
    }
  ],
  "annotations": [
    {
      "id": 9732435959,
      "image_id": 8341667948,
      "category_id": 1000000004,
      "segmentation": [],
      "area": 10784,
      "bbox": [
        38,
        15,
        216,
        209
      ]
    }
  ],
  "categories": [
    {
      "id": 1000000004,
      "name": "healthy",
      "supercategory": "Blueberry"
    }
  ]
}